pypbcms.py
pypbcms-1.1.1.dist-info/metadata.json
pypbcms-1.1.1.dist-info/entry_points.txt
pypbcms-1.1.1.dist-info/DESCRIPTION.rst
pypbcms-1.1.1.dist-info/WHEEL
pypbcms-1.1.1.dist-info/METADATA
pypbcms-1.1.1.dist-info/top_level.txt
pypbcms-1.1.1.dist-info/RECORD
