Metadata-Version: 2.0
Name: pypbcms
Version: 1.1.1
Summary: A plugin based cluster management system written in python
Home-page: https://github.com/bennr01/pypbcms/
Author: bennr01
Author-email: benjamin99.vogt@web.de
License: MIT
Keywords: cluster tools plugin plugins cmd rpc management
Platform: UNKNOWN
Classifier: Topic :: Utilities
Classifier: License :: OSI Approved :: MIT License
Requires-Dist: zope.interface
Requires-Dist: Twisted
